{"engineRunning": true, "kill": false, "riskOn": true, "lastRiskOn": true, "signalChange": false, "ratio": "1.2308", "ratioMA": "1.1554", "ratioDelta": "0.0754", "perfStartDate": "2025-01-03", "perfSpy": -100.0, "perfSpxl": 5679.6, "perfStrat": 2227.6, "useAclose": true, "equityFilename": "reports\\TReg_2025-01-03_2026-05-11_Equity.png", "ratioFilename": "reports\\TReg_2025-01-03_2026-05-11_Ratio.png", "lastTradeTime": "2026-01-22 12:45:00", "lastRecommendation": {"SPY": "0.00", "SPXL": "1.00", "SHV": "0.00"}, "signal_reason": "2026-05-09 06:36:49 \u2014 TurboRegime remains in a RiskOn++ (Turbo) regime as market conditions continue to support elevated exposure and trend participation. The current Turbo trade is now 22 trading days old and up approximately 28%, reflecting the type of sustained momentum move the system was designed to capture. While markets remain constructive, TReg continues to actively manage risk through disciplined regime logic and dynamic stop-limit protection designed to preserve gains if conditions deteriorate.", "engineHeartbeat": 0, "logs": [], "regime": "RiskOn++", "allocations": {"SPY": "0.00", "SPXL": "1.00", "SHV": "0.00"}, "regimeDays": 23, "regimeGain": 0.29175817335398313, "performance": {"meta": {"strategyName": "TReg", "riskOffSymbol": "SPY", "riskOnSymbol": "SPXL", "refSymbol": "SHV", "symbolPair": "SPY/SPXL", "startDate": "2025-01-03", "endDate": "2026-05-11", "periodYears": "1.35", "lastUpdated": "2026-05-11T17:45:04.080516"}, "current": {"totalReturnPct": "63.86", "cagrPct": "44.18", "maxDrawdownPct": "-15.30", "sharpe": "1.87", "mar": "2.89", "sortino": "3.31", "ulcer": "4.27", "upi": "9.42"}, "benchmarks": {"SPY": {"totalReturnPct": "26.70", "cagrPct": "19.16", "maxDrawdownPct": "-18.74", "sharpe": "1.06", "mar": "1.02", "sortino": "1.61", "ulcer": "4.32", "upi": "3.51"}, "SPXL": {"totalReturnPct": "55.90", "cagrPct": "38.96", "maxDrawdownPct": "-48.94", "sharpe": "0.89", "mar": "0.80", "sortino": "1.32", "ulcer": "14.16", "upi": "2.47"}, "SHV": {"totalReturnPct": "5.42", "cagrPct": "3.99", "maxDrawdownPct": "-0.01", "sharpe": "1022.43", "mar": "439.14", "sortino": "176.45", "ulcer": "0.00", "upi": "28.61"}}}, "boostTrigger": false, "regimeStartDate": "2026-04-09", "regimeSignalDate": "2026-04-08", "regimePeak": 0.29175817335398313, "regimePeakLimit": 0.17505490401238988, "regimePeakCapture": 1.0, "regimeMaxDD": -0.025384360000000106, "riskOnPPCurrent": 267.3, "riskOnPPEntry": 206.9, "riskOnPPStop": 243.11885964016346, "regimeEstGain": 0.2612}