{"performance": {"meta": {"strategyName": "TReg", "riskOffSymbol": "SPY", "riskOnSymbol": "SPXL", "refSymbol": "SHV", "symbolPair": "SPY/SPXL", "startDate": "2025-01-03 00:00:00", "endDate": "2026-05-06", "periodYears": "1.34", "lastUpdated": "2026-05-06T15:45:02.968132"}, "current": {"totalReturnPct": "55.00", "cagrPct": "38.82", "maxDrawdownPct": "-19.79", "sharpe": "1.57", "mar": "1.96", "sortino": "2.58", "ulcer": "6.18", "upi": "5.63"}, "benchmarks": {"SPY": {"totalReturnPct": "25.70", "cagrPct": "18.67", "maxDrawdownPct": "-18.74", "sharpe": "1.04", "mar": "1.00", "sortino": "1.57", "ulcer": "4.34", "upi": "3.38"}, "SPXL": {"totalReturnPct": "52.70", "cagrPct": "37.28", "maxDrawdownPct": "-48.94", "sharpe": "0.87", "mar": "0.76", "sortino": "1.28", "ulcer": "14.22", "upi": "2.34"}, "SHV": {"totalReturnPct": "5.37", "cagrPct": "3.99", "maxDrawdownPct": "-0.01", "sharpe": "1030.18", "mar": "439.72", "sortino": "175.40", "ulcer": "0.00", "upi": "0.00"}}}, "boostTrigger": false, "riskOn": true, "lastRiskOn": true, "signalChange": false, "regime": "RiskOn++", "regimeDays": 20, "regimeGain": 0.24019999999999997, "allocations": {"SPY": "0.00", "SPXL": "1.00", "SHV": "0.00"}, "ratioMA": "1.1308", "ratio": "1.2148", "ratioDelta": "0.0840", "equityFilename": "reports\\TReg_2025-01-03_2026-05-06_Equity.png", "ratioFilename": "reports\\TReg_2025-01-03_2026-05-06_Ratio.png"}